[
    {
        "id": 1,
        "name": "Pony",
        "URL": "pony.com",
        "description": "small four-legged creature for riding."
    },
    {
        "id": 2,
        "name": "Toy truck",
        "URL": "toytrucks.com",
        "description": "toy vehicle for driving around a toy town."
    },
    {
        "id": 3,
        "name": "Doll",
        "URL": "notcreepydolls.com",
        "description": "a smaller version of a person."
    },
    {
        "id": 4,
        "name": "Guitar",
        "URL": "guitars.com",
        "description": "a stringed instrument used to make music."
    }
]